pirate_weather/__init__.py
pirate_weather/api.py
pirate_weather/base.py
pirate_weather/exceptions.py
pirate_weather/forecast.py
pirate_weather/request_manager.py
pirate_weather/utils.py
pirate_weather/types/__init__.py
pirate_weather/types/languages.py
pirate_weather/types/units.py
pirate_weather/types/weather.py
pirateweather-1.0.0.dist-info/licenses/LICENSE
tests/__init__.py
tests/data.py
tests/mokcs.py
tests/test_base.py
tests/test_forecast.py
tests/utils.py
pirateweather-1.0.0.dist-info/METADATA
pirateweather-1.0.0.dist-info/WHEEL
pirateweather-1.0.0.dist-info/top_level.txt
pirateweather-1.0.0.dist-info/RECORD
