Metadata-Version: 2.4
Name: pirateweather
Version: 1.0.0
Summary: The Pirate Weather API wrapper
Home-page: https://github.com/Pirate-Weather/pirate-weather-python
Download-URL: https://github.com/Pirate-Weather/pirate-weather-python/archive/1.0.0.tar.gz
Author: Pirate-Weather
License: GPLv3 License
Classifier: Environment :: Web Environment
Classifier: Intended Audience :: Developers
Classifier: License :: OSI Approved :: MIT License
Classifier: Programming Language :: Python :: 3.12
Classifier: Topic :: Software Development :: Libraries :: Python Modules
License-File: LICENSE
Requires-Dist: requests==2.32.5
Requires-Dist: pytz==2025.2
Requires-Dist: aiohttp==3.13.2
Dynamic: author
Dynamic: classifier
Dynamic: description
Dynamic: description-content-type
Dynamic: download-url
Dynamic: home-page
Dynamic: license
Dynamic: license-file
Dynamic: requires-dist
Dynamic: summary
